NOTICE
asyncio_gevent-0.2.5.dist-info/METADATA
asyncio_gevent-0.2.5.dist-info/WHEEL
asyncio_gevent-0.2.5.dist-info/entry_points.txt
asyncio_gevent-0.2.5.dist-info/licenses/LICENSE
asyncio_gevent/__init__.py
asyncio_gevent/async_to_sync.py
asyncio_gevent/event_loop.py
asyncio_gevent/event_loop_policy.py
asyncio_gevent/future_to_greenlet.py
asyncio_gevent/gevent_loop/__init__.py
asyncio_gevent/gevent_loop/async_watcher.py
asyncio_gevent/gevent_loop/callback.py
asyncio_gevent/gevent_loop/child_watcher.py
asyncio_gevent/gevent_loop/fork_watcher.py
asyncio_gevent/gevent_loop/gevent_loop.py
asyncio_gevent/gevent_loop/io_watcher.py
asyncio_gevent/gevent_loop/monkey_jail.py
asyncio_gevent/gevent_loop/ref_mixin.py
asyncio_gevent/gevent_loop/signal_watcher.py
asyncio_gevent/gevent_loop/timer_watcher.py
asyncio_gevent/gevent_loop/watcher.py
asyncio_gevent/greenlet_to_future.py
asyncio_gevent/sync_to_async.py
asyncio_gevent-0.2.5.dist-info/RECORD
