Metadata-Version: 2.1
Name: asyncio-gevent
Version: 0.2.5
Summary: asyncio & gevent in harmony
Keywords: asyncio,gevent
Author-Email: =?utf-8?q?Fr=C3=A9d=C3=A9rique_Mittelstaedt?= <hi@gfm.io>
License: MIT License
Classifier: Development Status :: 4 - Beta
Classifier: Intended Audience :: Developers
Classifier: License :: OSI Approved :: MIT License
Classifier: Programming Language :: Python :: 3
Classifier: Programming Language :: Python :: 3.7
Classifier: Programming Language :: Python :: 3.8
Classifier: Programming Language :: Python :: 3.9
Classifier: Programming Language :: Python :: 3.10
Classifier: Programming Language :: Python :: 3.11
Classifier: Programming Language :: Python :: 3.12
Classifier: Programming Language :: Python :: 3.13
Classifier: Programming Language :: Python :: Implementation :: CPython
Classifier: Programming Language :: Python :: Implementation :: PyPy
Classifier: Topic :: Software Development :: Libraries
Classifier: Topic :: Software Development :: Libraries :: Python Modules
Project-URL: homepage, https://github.com/gfmio/asyncio-gevent
Project-URL: repository, https://github.com/gfmio/asyncio-gevent
Project-URL: documentation, https://github.com/gfmio/asyncio-gevent
Requires-Python: <4.0,>=3.7
Requires-Dist: gevent<22.10.0,>=1.3; python_version >= "3.7" and python_version < "3.8"
Requires-Dist: gevent<24.10.1,>=1.5; python_version >= "3.8" and python_version < "3.9"
Requires-Dist: gevent>=20.6.0; python_version >= "3.9" and python_version < "3.10"
Requires-Dist: gevent>=21.8.0; python_version >= "3.10" and python_version < "3.11"
Requires-Dist: gevent>=22.08.0; python_version >= "3.11" and python_version < "3.12"
Requires-Dist: gevent>=23.7.0; python_version >= "3.12" and python_version < "3.13"
Requires-Dist: gevent>=24.10.1; python_version >= "3.13"
Requires-Dist: greenlet<=3.1.0,>=0.4.13; python_version >= "3.7" and python_version < "3.8"
Requires-Dist: greenlet<=3.1.0,>=0.4.13; python_version >= "3.8" and python_version < "3.9"
Requires-Dist: greenlet>=0.4.16; python_version >= "3.9" and python_version < "3.10"
Requires-Dist: greenlet>=1.1.0; python_version >= "3.10" and python_version < "3.11"
Requires-Dist: greenlet>=1.1.3; python_version >= "3.11" and python_version < "3.12"
Requires-Dist: greenlet>=3.1.0; python_version >= "3.12"
